opencanary/__init__.py
opencanary/__main__.py
opencanary/app.py
opencanary/cli.py
opencanary/config.py
opencanary/honeycred.py
opencanary/logger.py
opencanary/data/settings-usermodule.json
opencanary/data/settings.json
opencanary/modules/__init__.py
opencanary/modules/des.py
opencanary/modules/example0.py
opencanary/modules/example1.py
opencanary/modules/ftp.py
opencanary/modules/http.py
opencanary/modules/httpproxy.py
opencanary/modules/mssql.py
opencanary/modules/mysql.py
opencanary/modules/ntp.py
opencanary/modules/portscan.py
opencanary/modules/rdp.py
opencanary/modules/samba.py
opencanary/modules/sip.py
opencanary/modules/snmp.py
opencanary/modules/ssh.py
opencanary/modules/telnet.py
opencanary/modules/testpdf.py
opencanary/modules/tftp.py
opencanary/modules/vnc.py
opencanary/modules/data/http/skin/basicLogin/403.html
opencanary/modules/data/http/skin/basicLogin/404.html
opencanary/modules/data/http/skin/basicLogin/index.html
opencanary/modules/data/http/skin/basicLogin2/403.html
opencanary/modules/data/http/skin/basicLogin2/404.html
opencanary/modules/data/http/skin/basicLogin2/index.html
opencanary/modules/data/http/skin/defaultApache/403.html
opencanary/modules/data/http/skin/defaultApache/404.html
opencanary/modules/data/http/skin/defaultApache/index.htm
opencanary/modules/data/http/skin/defaultApache/static/apache_pb2.gif
opencanary/modules/data/http/skin/iis7/index.html
opencanary/modules/data/http/skin/iis7/static/welcome.png
opencanary/modules/data/http/skin/nasLogin/403.html
opencanary/modules/data/http/skin/nasLogin/404.html
opencanary/modules/data/http/skin/nasLogin/index.html
opencanary/modules/data/http/skin/nasLogin/static/css/desktop.css
opencanary/modules/data/http/skin/nasLogin/static/css/ext-all.css
opencanary/modules/data/http/skin/nasLogin/static/css/style.css
opencanary/modules/data/http/skin/nasLogin/static/css/ux-all.css
opencanary/modules/data/http/skin/nasLogin/static/css/xtheme-gray.css
patron_it_opencanary-0.7.1.dist-info/LICENSE
patron_it_opencanary-0.7.1.dist-info/METADATA
patron_it_opencanary-0.7.1.dist-info/WHEEL
patron_it_opencanary-0.7.1.dist-info/entry_points.txt
patron_it_opencanary-0.7.1.dist-info/top_level.txt
patron_it_opencanary-0.7.1.dist-info/RECORD
