Metadata-Version: 2.1
Name: patron-it-opencanary
Version: 0.7.1
Summary: OpenCanary daemon
Home-page: https://github.com/patron-it/opencanary
Author: Thinkst Applied Research
Author-email: info@thinkst.com
Maintainer: PATRON-IT
Maintainer-email: martin.haller+opencanary-pypi@patron-it.cz
License: BSD 3-Clause License
Project-URL: CI: Travis, https://travis-ci.com/patron-it/opencanary
Project-URL: Docs: RTD, https://patron-it-opencanary.readthedocs.io
Project-URL: GitHub: issues, https://github.com/patron-it/opencanary/issues
Project-URL: GitHub: repo, https://github.com/patron-it/opencanary
Keywords: canary,honeypot,monitoring,network,security
Platform: any
Classifier: Development Status :: 5 - Production/Stable
Classifier: Environment :: Console
Classifier: Framework :: Twisted
Classifier: Intended Audience :: Developers
Classifier: Intended Audience :: Information Technology
Classifier: Intended Audience :: Science/Research
Classifier: Intended Audience :: System Administrators
Classifier: License :: OSI Approved :: BSD License
Classifier: Operating System :: POSIX
Classifier: Programming Language :: Python
Classifier: Programming Language :: Python :: 2
Classifier: Programming Language :: Python :: 2.7
Classifier: Programming Language :: Python :: 3
Classifier: Programming Language :: Python :: 3.4
Classifier: Programming Language :: Python :: 3.5
Classifier: Programming Language :: Python :: 3.6
Classifier: Programming Language :: Python :: 3.7
Classifier: Programming Language :: Python :: Implementation
Classifier: Programming Language :: Python :: Implementation :: CPython
Classifier: Programming Language :: Python :: Implementation :: Jython
Classifier: Programming Language :: Python :: Implementation :: PyPy
Classifier: Topic :: Internet
Classifier: Topic :: Internet :: Log Analysis
Classifier: Topic :: Scientific/Engineering
Classifier: Topic :: Security
Classifier: Topic :: Software Development :: Embedded Systems
Classifier: Topic :: System
Classifier: Topic :: System :: Logging
Classifier: Topic :: System :: Monitoring
Classifier: Topic :: System :: Networking :: Monitoring
Requires-Python: >=2.7,!=3.0.*,!=3.1.*,!=3.2.*,!=3.3.*
Requires-Dist: Twisted (==18.7.0)
Requires-Dist: pyasn1 (==0.4.4)
Requires-Dist: cryptography (==2.3.0)
Requires-Dist: simplejson (==3.16.0)
Requires-Dist: zope.interface (==4.5.0)
Requires-Dist: PyPDF2 (==1.26.0)
Requires-Dist: fpdf (==1.7.2)
Requires-Dist: passlib (==1.7.1)
Requires-Dist: Jinja2 (==2.10.0)
Requires-Dist: ntlmlib (==0.72)
Requires-Dist: python-dateutil
Requires-Dist: click (==6.7)
Requires-Dist: six
Requires-Dist: daemonocle
Requires-Dist: wsgiref (==0.1.2) ; python_version < "3"
Provides-Extra: dshield
Requires-Dist: requests ; extra == 'dshield'
Provides-Extra: rdp
Requires-Dist: rdpy ; extra == 'rdp'
Provides-Extra: remote_logging
Requires-Dist: treq ; extra == 'remote_logging'
Provides-Extra: snmp
Requires-Dist: scapy ; extra == 'snmp'
Requires-Dist: pcapy ; extra == 'snmp'
